eresponse/__init__.py
eresponse/models.py
eresponse/resp.py
eresponse-1.0.1.dist-info/LICENSE
eresponse-1.0.1.dist-info/METADATA
eresponse-1.0.1.dist-info/WHEEL
eresponse-1.0.1.dist-info/top_level.txt
eresponse-1.0.1.dist-info/RECORD
