Metadata-Version: 2.1
Name: eresponse
Version: 1.0.1
Summary: UNKNOWN
Home-page: http://github.com/Beaxhem/eresponse
Author: beaxhem
Author-email: senchukov02@gmail.com
License: mit
Platform: UNKNOWN
Classifier: Programming Language :: Python :: 3
Classifier: License :: OSI Approved :: MIT License
Classifier: Operating System :: OS Independent
Requires-Dist: flask
